acontext/__init__.py
acontext/_constants.py
acontext/_utils.py
acontext/agent/__init__.py
acontext/agent/base.py
acontext/agent/disk.py
acontext/agent/prompts.py
acontext/agent/sandbox.py
acontext/agent/skill.py
acontext/agent/text_editor.py
acontext/async_client.py
acontext/client.py
acontext/client_types.py
acontext/errors.py
acontext/messages.py
acontext/py.typed
acontext/resources/__init__.py
acontext/resources/async_disks.py
acontext/resources/async_sandboxes.py
acontext/resources/async_sessions.py
acontext/resources/async_skills.py
acontext/resources/async_tools.py
acontext/resources/async_users.py
acontext/resources/disks.py
acontext/resources/sandboxes.py
acontext/resources/sessions.py
acontext/resources/skills.py
acontext/resources/tools.py
acontext/resources/users.py
acontext/types/__init__.py
acontext/types/common.py
acontext/types/disk.py
acontext/types/sandbox.py
acontext/types/session.py
acontext/types/skill.py
acontext/types/tool.py
acontext/types/user.py
acontext/uploads.py
acontext-0.1.7.dist-info/WHEEL
acontext-0.1.7.dist-info/METADATA
acontext-0.1.7.dist-info/RECORD
