Metadata-Version: 2.3
Name: acontext
Version: 0.1.7
Summary: Python SDK for the Acontext API
Keywords: acontext,sdk,client,api
Requires-Dist: httpx>=0.28.1
Requires-Dist: openai>=2.6.1
Requires-Dist: anthropic>=0.72.0
Requires-Dist: pydantic>=2.12.3
Requires-Dist: urllib3>=2.6.3
Requires-Python: >=3.10
Project-URL: Homepage, https://github.com/memodb-io/Acontext
Project-URL: Repository, https://github.com/memodb-io/Acontext
Project-URL: Issues, https://github.com/memodb-io/Acontext/issues
